<?xml version="1.0" encoding="UTF-8"?><phone_book>   <person>      <name>Jane Doe</name>    <!-- XPATH:  /phone_book/person/phone[@brand='lucent']/../name -->      <phone location="work" brand="lucent">303-555-1212</phone>      <company>Sun Microsystem Inc.</company> <!-- XPATH: /phone_book/person/phone[@brand='lucent']/ancestor::person/company -->   </person>   <person>      <name>John Smith</name>    <!-- XPATH: /phone_book/person/phone[(@location='home') and (contains(.,'301'))]/../name -->      <phone location="home">301-555-1212</phone>      <company>Sun Microsystem Inc.</company>   </person>   <person>      <name>Joe Jones</name>  <!-- XPATH:  /phone_book/person/name[contains(.,'Joe')] -->      <phone location="mobile" brand="nokia">201-555-1212</phone>      <company>Sun Microsystem Inc.</company>   </person></phone_book>